<INVARIANTS>
<!-- =========================================================================== -->
<PPT>
<PPTNAME>aprogram.point:::Trust_Human_Dec</PPTNAME>
<INVINFO> <PARENT>Trust_Human_Dec</PARENT> <INV>Alarm_M2H == EventN_Machine</INV> <SAMPLES>2</SAMPLES> <DAIKON>Alarm_M2H == EventN_Machine</DAIKON> <DAIKONCLASS>class daikon.inv.binary.twoString.StringEqual</DAIKONCLASS>  </INVINFO>
<INVINFO> <PARENT>Trust_Human_Dec</PARENT> <INV>Alarm_M2H == EventW_Machine</INV> <SAMPLES>2</SAMPLES> <DAIKON>Alarm_M2H == EventW_Machine</DAIKON> <DAIKONCLASS>class daikon.inv.binary.twoString.StringEqual</DAIKONCLASS>  </INVINFO>
<INVINFO> <PARENT>Trust_Human_Dec</PARENT> <INV>ManualBrake_H2M == ManualThrottle_H2M</INV> <SAMPLES>2</SAMPLES> <DAIKON>ManualBrake_H2M == ManualThrottle_H2M</DAIKON> <DAIKONCLASS>class daikon.inv.binary.twoScalar.FloatEqual</DAIKONCLASS>  </INVINFO>
<INVINFO> <PARENT>Trust_Human_Dec</PARENT> <INV>ManualBrake_H2M == CurrentBrake_Machine</INV> <SAMPLES>2</SAMPLES> <DAIKON>ManualBrake_H2M == CurrentBrake_Machine</DAIKON> <DAIKONCLASS>class daikon.inv.binary.twoScalar.FloatEqual</DAIKONCLASS>  </INVINFO>
<INVINFO> <PARENT>Trust_Human_Dec</PARENT> <INV>ManualBrake_H2M == AutoBrake_Machine</INV> <SAMPLES>2</SAMPLES> <DAIKON>ManualBrake_H2M == AutoBrake_Machine</DAIKON> <DAIKONCLASS>class daikon.inv.binary.twoScalar.FloatEqual</DAIKONCLASS>  </INVINFO>
<INVINFO> <PARENT>Trust_Human_Dec</PARENT> <INV>ManualBrake_H2M == RangeN_Machine</INV> <SAMPLES>2</SAMPLES> <DAIKON>ManualBrake_H2M == RangeN_Machine</DAIKON> <DAIKONCLASS>class daikon.inv.binary.twoScalar.FloatEqual</DAIKONCLASS>  </INVINFO>
<INVINFO> <PARENT>Trust_Human_Dec</PARENT> <INV>ManualBrake_H2M == RangeW_Machine</INV> <SAMPLES>2</SAMPLES> <DAIKON>ManualBrake_H2M == RangeW_Machine</DAIKON> <DAIKONCLASS>class daikon.inv.binary.twoScalar.FloatEqual</DAIKONCLASS>  </INVINFO>
<INVINFO> <PARENT>Trust_Human_Dec</PARENT> <INV>ManualBrake_H2M == Reliability_Machine</INV> <SAMPLES>2</SAMPLES> <DAIKON>ManualBrake_H2M == Reliability_Machine</DAIKON> <DAIKONCLASS>class daikon.inv.binary.twoScalar.FloatEqual</DAIKONCLASS>  </INVINFO>
<INVINFO> <PARENT>Trust_Human_Dec</PARENT> <INV>ManualGear_H2M == CurrentGear_Machine</INV> <SAMPLES>2</SAMPLES> <DAIKON>ManualGear_H2M == CurrentGear_Machine</DAIKON> <DAIKONCLASS>class daikon.inv.binary.twoScalar.FloatEqual</DAIKONCLASS>  </INVINFO>
<INVINFO> <PARENT>Trust_Human_Dec</PARENT> <INV>ManualGear_H2M == AutoGear_Machine</INV> <SAMPLES>2</SAMPLES> <DAIKON>ManualGear_H2M == AutoGear_Machine</DAIKON> <DAIKONCLASS>class daikon.inv.binary.twoScalar.FloatEqual</DAIKONCLASS>  </INVINFO>
<INVINFO> <PARENT>Trust_Human_Dec</PARENT> <INV>CurrentWheel_Machine == AutoWheel_Machine</INV> <SAMPLES>2</SAMPLES> <DAIKON>CurrentWheel_Machine == AutoWheel_Machine</DAIKON> <DAIKONCLASS>class daikon.inv.binary.twoScalar.FloatEqual</DAIKONCLASS>  </INVINFO>
<INVINFO> <PARENT>Trust_Human_Dec</PARENT> <INV>CurrentThrottle_Machine == AutoThrottle_Machine</INV> <SAMPLES>2</SAMPLES> <DAIKON>CurrentThrottle_Machine == AutoThrottle_Machine</DAIKON> <DAIKONCLASS>class daikon.inv.binary.twoScalar.FloatEqual</DAIKONCLASS>  </INVINFO>
<INVINFO> <PARENT>Trust_Human_Dec</PARENT> <INV>TimeSignal_Sec one of { 64.0, 65.0 }</INV> <SAMPLES>2</SAMPLES> <DAIKON>TimeSignal_Sec one of { 64.0, 65.0 }</DAIKON> <DAIKONCLASS>class daikon.inv.unary.scalar.OneOfFloat</DAIKONCLASS>  </INVINFO>
<INVINFO> <PARENT>Trust_Human_Dec</PARENT> <INV>Trust_Human one of { 3.0, 4.0 }</INV> <SAMPLES>2</SAMPLES> <DAIKON>Trust_Human one of { 3.0, 4.0 }</DAIKON> <DAIKONCLASS>class daikon.inv.unary.scalar.OneOfFloat</DAIKONCLASS>  </INVINFO>
<INVINFO> <PARENT>Trust_Human_Dec</PARENT> <INV>Alarm_M2H == &quot; &quot;</INV> <SAMPLES>2</SAMPLES> <DAIKON>Alarm_M2H == &quot; &quot;</DAIKON> <DAIKONCLASS>class daikon.inv.unary.string.OneOfString</DAIKONCLASS>  </INVINFO>
<INVINFO> <PARENT>Trust_Human_Dec</PARENT> <INV>Mode_H2M == &quot;autonomous&quot;</INV> <SAMPLES>2</SAMPLES> <DAIKON>Mode_H2M == &quot;autonomous&quot;</DAIKON> <DAIKONCLASS>class daikon.inv.unary.string.OneOfString</DAIKONCLASS>  </INVINFO>
<INVINFO> <PARENT>Trust_Human_Dec</PARENT> <INV>ManualBrake_H2M == 0.0</INV> <SAMPLES>2</SAMPLES> <DAIKON>ManualBrake_H2M == 0.0</DAIKON> <DAIKONCLASS>class daikon.inv.unary.scalar.OneOfFloat</DAIKONCLASS>  </INVINFO>
<INVINFO> <PARENT>Trust_Human_Dec</PARENT> <INV>ManualGear_H2M == 1.0</INV> <SAMPLES>2</SAMPLES> <DAIKON>ManualGear_H2M == 1.0</DAIKON> <DAIKONCLASS>class daikon.inv.unary.scalar.OneOfFloat</DAIKONCLASS>  </INVINFO>
<INVINFO> <PARENT>Trust_Human_Dec</PARENT> <INV>ManualWheel_H2M == -0.03433279926755972</INV> <SAMPLES>2</SAMPLES> <DAIKON>ManualWheel_H2M == -0.03433279926755972</DAIKON> <DAIKONCLASS>class daikon.inv.unary.scalar.OneOfFloat</DAIKONCLASS>  </INVINFO>
<INVINFO> <PARENT>Trust_Human_Dec</PARENT> <INV>CurrentWheel_Machine one of { 21.40611880183402, 23.626434035474205 }</INV> <SAMPLES>2</SAMPLES> <DAIKON>CurrentWheel_Machine one of { 21.40611880183402, 23.626434035474205 }</DAIKON> <DAIKONCLASS>class daikon.inv.unary.scalar.OneOfFloat</DAIKONCLASS>  </INVINFO>
<INVINFO> <PARENT>Trust_Human_Dec</PARENT> <INV>CurrentThrottle_Machine one of { 15.0, 20.0 }</INV> <SAMPLES>2</SAMPLES> <DAIKON>CurrentThrottle_Machine one of { 15.0, 20.0 }</DAIKON> <DAIKONCLASS>class daikon.inv.unary.scalar.OneOfFloat</DAIKONCLASS>  </INVINFO>
<INVINFO> <PARENT>Trust_Human_Dec</PARENT> <INV>Speed_Machine one of { 15.641188972717135, 15.674522683139939 }</INV> <SAMPLES>2</SAMPLES> <DAIKON>Speed_Machine one of { 15.641188972717135, 15.674522683139939 }</DAIKON> <DAIKONCLASS>class daikon.inv.unary.scalar.OneOfFloat</DAIKONCLASS>  </INVINFO>
<INVINFO> <PARENT>Trust_Human_Dec</PARENT> <INV>PupilLeft_Human one of { 3.82, 4.03 }</INV> <SAMPLES>2</SAMPLES> <DAIKON>PupilLeft_Human one of { 3.82, 4.03 }</DAIKON> <DAIKONCLASS>class daikon.inv.unary.scalar.OneOfFloat</DAIKONCLASS>  </INVINFO>
<INVINFO> <PARENT>Trust_Human_Dec</PARENT> <INV>PupilRight_Human one of { 3.77, 3.83 }</INV> <SAMPLES>2</SAMPLES> <DAIKON>PupilRight_Human one of { 3.77, 3.83 }</DAIKON> <DAIKONCLASS>class daikon.inv.unary.scalar.OneOfFloat</DAIKONCLASS>  </INVINFO>
<INVINFO> <PARENT>Trust_Human_Dec</PARENT> <INV>GSR_Human one of { 111.338736973368, 115.649720127677 }</INV> <SAMPLES>2</SAMPLES> <DAIKON>GSR_Human one of { 111.338736973368, 115.649720127677 }</DAIKON> <DAIKONCLASS>class daikon.inv.unary.scalar.OneOfFloat</DAIKONCLASS>  </INVINFO>
<INVINFO> <PARENT>Trust_Human_Dec</PARENT> <INV>PupilChange_Human one of { -0.4649999999999994, -0.13500000000000023 }</INV> <SAMPLES>2</SAMPLES> <DAIKON>PupilChange_Human one of { -0.4649999999999994, -0.13500000000000023 }</DAIKON> <DAIKONCLASS>class daikon.inv.unary.scalar.OneOfFloat</DAIKONCLASS>  </INVINFO>
<INVINFO> <PARENT>Trust_Human_Dec</PARENT> <INV>AverageTrust_Human == 4.060773480662983</INV> <SAMPLES>2</SAMPLES> <DAIKON>AverageTrust_Human == 4.060773480662983</DAIKON> <DAIKONCLASS>class daikon.inv.unary.scalar.OneOfFloat</DAIKONCLASS>  </INVINFO>
<INVINFO> <PARENT>Trust_Human_Dec</PARENT> <INV>TrustChange_Human == -1.0</INV> <SAMPLES>2</SAMPLES> <DAIKON>TrustChange_Human == -1.0</DAIKON> <DAIKONCLASS>class daikon.inv.unary.scalar.OneOfFloat</DAIKONCLASS>  </INVINFO>
</PPT>
<!-- =========================================================================== -->
<PPT>
<PPTNAME>aprogram.point:::Trust_Human_Inc</PPTNAME>
<INVINFO> <PARENT>Trust_Human_Inc</PARENT> <INV>Alarm_M2H == EventN_Machine</INV> <SAMPLES>3</SAMPLES> <DAIKON>Alarm_M2H == EventN_Machine</DAIKON> <DAIKONCLASS>class daikon.inv.binary.twoString.StringEqual</DAIKONCLASS>  </INVINFO>
<INVINFO> <PARENT>Trust_Human_Inc</PARENT> <INV>Alarm_M2H == EventW_Machine</INV> <SAMPLES>3</SAMPLES> <DAIKON>Alarm_M2H == EventW_Machine</DAIKON> <DAIKONCLASS>class daikon.inv.binary.twoString.StringEqual</DAIKONCLASS>  </INVINFO>
<INVINFO> <PARENT>Trust_Human_Inc</PARENT> <INV>ManualBrake_H2M == ManualThrottle_H2M</INV> <SAMPLES>3</SAMPLES> <DAIKON>ManualBrake_H2M == ManualThrottle_H2M</DAIKON> <DAIKONCLASS>class daikon.inv.binary.twoScalar.FloatEqual</DAIKONCLASS>  </INVINFO>
<INVINFO> <PARENT>Trust_Human_Inc</PARENT> <INV>ManualBrake_H2M == CurrentBrake_Machine</INV> <SAMPLES>3</SAMPLES> <DAIKON>ManualBrake_H2M == CurrentBrake_Machine</DAIKON> <DAIKONCLASS>class daikon.inv.binary.twoScalar.FloatEqual</DAIKONCLASS>  </INVINFO>
<INVINFO> <PARENT>Trust_Human_Inc</PARENT> <INV>ManualBrake_H2M == AutoBrake_Machine</INV> <SAMPLES>3</SAMPLES> <DAIKON>ManualBrake_H2M == AutoBrake_Machine</DAIKON> <DAIKONCLASS>class daikon.inv.binary.twoScalar.FloatEqual</DAIKONCLASS>  </INVINFO>
<INVINFO> <PARENT>Trust_Human_Inc</PARENT> <INV>ManualBrake_H2M == RangeN_Machine</INV> <SAMPLES>3</SAMPLES> <DAIKON>ManualBrake_H2M == RangeN_Machine</DAIKON> <DAIKONCLASS>class daikon.inv.binary.twoScalar.FloatEqual</DAIKONCLASS>  </INVINFO>
<INVINFO> <PARENT>Trust_Human_Inc</PARENT> <INV>ManualBrake_H2M == RangeW_Machine</INV> <SAMPLES>3</SAMPLES> <DAIKON>ManualBrake_H2M == RangeW_Machine</DAIKON> <DAIKONCLASS>class daikon.inv.binary.twoScalar.FloatEqual</DAIKONCLASS>  </INVINFO>
<INVINFO> <PARENT>Trust_Human_Inc</PARENT> <INV>ManualBrake_H2M == Reliability_Machine</INV> <SAMPLES>3</SAMPLES> <DAIKON>ManualBrake_H2M == Reliability_Machine</DAIKON> <DAIKONCLASS>class daikon.inv.binary.twoScalar.FloatEqual</DAIKONCLASS>  </INVINFO>
<INVINFO> <PARENT>Trust_Human_Inc</PARENT> <INV>ManualGear_H2M == CurrentGear_Machine</INV> <SAMPLES>3</SAMPLES> <DAIKON>ManualGear_H2M == CurrentGear_Machine</DAIKON> <DAIKONCLASS>class daikon.inv.binary.twoScalar.FloatEqual</DAIKONCLASS>  </INVINFO>
<INVINFO> <PARENT>Trust_Human_Inc</PARENT> <INV>ManualGear_H2M == AutoGear_Machine</INV> <SAMPLES>3</SAMPLES> <DAIKON>ManualGear_H2M == AutoGear_Machine</DAIKON> <DAIKONCLASS>class daikon.inv.binary.twoScalar.FloatEqual</DAIKONCLASS>  </INVINFO>
<INVINFO> <PARENT>Trust_Human_Inc</PARENT> <INV>ManualGear_H2M == TrustChange_Human</INV> <SAMPLES>3</SAMPLES> <DAIKON>ManualGear_H2M == TrustChange_Human</DAIKON> <DAIKONCLASS>class daikon.inv.binary.twoScalar.FloatEqual</DAIKONCLASS>  </INVINFO>
<INVINFO> <PARENT>Trust_Human_Inc</PARENT> <INV>CurrentWheel_Machine == AutoWheel_Machine</INV> <SAMPLES>3</SAMPLES> <DAIKON>CurrentWheel_Machine == AutoWheel_Machine</DAIKON> <DAIKONCLASS>class daikon.inv.binary.twoScalar.FloatEqual</DAIKONCLASS>  </INVINFO>
<INVINFO> <PARENT>Trust_Human_Inc</PARENT> <INV>CurrentThrottle_Machine == AutoThrottle_Machine</INV> <SAMPLES>3</SAMPLES> <DAIKON>CurrentThrottle_Machine == AutoThrottle_Machine</DAIKON> <DAIKONCLASS>class daikon.inv.binary.twoScalar.FloatEqual</DAIKONCLASS>  </INVINFO>
<INVINFO> <PARENT>Trust_Human_Inc</PARENT> <INV>TimeSignal_Sec one of { 20.0, 25.0, 73.0 }</INV> <SAMPLES>3</SAMPLES> <DAIKON>TimeSignal_Sec one of { 20.0, 25.0, 73.0 }</DAIKON> <DAIKONCLASS>class daikon.inv.unary.scalar.OneOfFloat</DAIKONCLASS>  </INVINFO>
<INVINFO> <PARENT>Trust_Human_Inc</PARENT> <INV>Trust_Human one of { 4.0, 5.0 }</INV> <SAMPLES>3</SAMPLES> <DAIKON>Trust_Human one of { 4.0, 5.0 }</DAIKON> <DAIKONCLASS>class daikon.inv.unary.scalar.OneOfFloat</DAIKONCLASS>  </INVINFO>
<INVINFO> <PARENT>Trust_Human_Inc</PARENT> <INV>Alarm_M2H == &quot; &quot;</INV> <SAMPLES>3</SAMPLES> <DAIKON>Alarm_M2H == &quot; &quot;</DAIKON> <DAIKONCLASS>class daikon.inv.unary.string.OneOfString</DAIKONCLASS>  </INVINFO>
<INVINFO> <PARENT>Trust_Human_Inc</PARENT> <INV>Mode_H2M == &quot;autonomous&quot;</INV> <SAMPLES>3</SAMPLES> <DAIKON>Mode_H2M == &quot;autonomous&quot;</DAIKON> <DAIKONCLASS>class daikon.inv.unary.string.OneOfString</DAIKONCLASS>  </INVINFO>
<INVINFO> <PARENT>Trust_Human_Inc</PARENT> <INV>ManualBrake_H2M == 0.0</INV> <SAMPLES>3</SAMPLES> <DAIKON>ManualBrake_H2M == 0.0</DAIKON> <DAIKONCLASS>class daikon.inv.unary.scalar.OneOfFloat</DAIKONCLASS>  </INVINFO>
<INVINFO> <PARENT>Trust_Human_Inc</PARENT> <INV>ManualGear_H2M == 1.0</INV> <SAMPLES>3</SAMPLES> <DAIKON>ManualGear_H2M == 1.0</DAIKON> <DAIKONCLASS>class daikon.inv.unary.scalar.OneOfFloat</DAIKONCLASS>  </INVINFO>
<INVINFO> <PARENT>Trust_Human_Inc</PARENT> <INV>ManualWheel_H2M == -0.03433279926755972</INV> <SAMPLES>3</SAMPLES> <DAIKON>ManualWheel_H2M == -0.03433279926755972</DAIKON> <DAIKONCLASS>class daikon.inv.unary.scalar.OneOfFloat</DAIKONCLASS>  </INVINFO>
<INVINFO> <PARENT>Trust_Human_Inc</PARENT> <INV>CurrentWheel_Machine one of { -8.8131194754002, 9.565349660339822E-4, 0.006031404708155632 }</INV> <SAMPLES>3</SAMPLES> <DAIKON>CurrentWheel_Machine one of { -8.8131194754002, 9.565349660339822E-4, 0.006031404708155632 }</DAIKON> <DAIKONCLASS>class daikon.inv.unary.scalar.OneOfFloat</DAIKONCLASS>  </INVINFO>
<INVINFO> <PARENT>Trust_Human_Inc</PARENT> <INV>CurrentThrottle_Machine one of { 15.0, 20.0 }</INV> <SAMPLES>3</SAMPLES> <DAIKON>CurrentThrottle_Machine one of { 15.0, 20.0 }</DAIKON> <DAIKONCLASS>class daikon.inv.unary.scalar.OneOfFloat</DAIKONCLASS>  </INVINFO>
<INVINFO> <PARENT>Trust_Human_Inc</PARENT> <INV>Speed_Machine one of { 11.231655768644004, 12.247602462484126, 15.670951593544716 }</INV> <SAMPLES>3</SAMPLES> <DAIKON>Speed_Machine one of { 11.231655768644004, 12.247602462484126, 15.670951593544716 }</DAIKON> <DAIKONCLASS>class daikon.inv.unary.scalar.OneOfFloat</DAIKONCLASS>  </INVINFO>
<INVINFO> <PARENT>Trust_Human_Inc</PARENT> <INV>PupilLeft_Human one of { 3.42, 5.0 }</INV> <SAMPLES>3</SAMPLES> <DAIKON>PupilLeft_Human one of { 3.42, 5.0 }</DAIKON> <DAIKONCLASS>class daikon.inv.unary.scalar.OneOfFloat</DAIKONCLASS>  </INVINFO>
<INVINFO> <PARENT>Trust_Human_Inc</PARENT> <INV>PupilRight_Human one of { 3.5, 3.73, 5.0 }</INV> <SAMPLES>3</SAMPLES> <DAIKON>PupilRight_Human one of { 3.5, 3.73, 5.0 }</DAIKON> <DAIKONCLASS>class daikon.inv.unary.scalar.OneOfFloat</DAIKONCLASS>  </INVINFO>
<INVINFO> <PARENT>Trust_Human_Inc</PARENT> <INV>GSR_Human one of { 129.295854774896, 148.235991698784, 151.634621216716 }</INV> <SAMPLES>3</SAMPLES> <DAIKON>GSR_Human one of { 129.295854774896, 148.235991698784, 151.634621216716 }</DAIKON> <DAIKONCLASS>class daikon.inv.unary.scalar.OneOfFloat</DAIKONCLASS>  </INVINFO>
<INVINFO> <PARENT>Trust_Human_Inc</PARENT> <INV>PupilChange_Human one of { -0.2549999999999999, 0.42500000000000027, 1.3049999999999997 }</INV> <SAMPLES>3</SAMPLES> <DAIKON>PupilChange_Human one of { -0.2549999999999999, 0.42500000000000027, 1.3049999999999997 }</DAIKON> <DAIKONCLASS>class daikon.inv.unary.scalar.OneOfFloat</DAIKONCLASS>  </INVINFO>
<INVINFO> <PARENT>Trust_Human_Inc</PARENT> <INV>AverageTrust_Human == 4.060773480662983</INV> <SAMPLES>3</SAMPLES> <DAIKON>AverageTrust_Human == 4.060773480662983</DAIKON> <DAIKONCLASS>class daikon.inv.unary.scalar.OneOfFloat</DAIKONCLASS>  </INVINFO>
</PPT>
</INVARIANTS>
